.project-version
LICENSE
MANIFEST.in
README.md
pyproject.toml
setup.cfg
setup.py
requirements/project.txt
threads/__init__.py
threads/main.py
threads/settings.py
threads/utils.py
threads/apis/__init__.py
threads/apis/abstract.py
threads/apis/private.py
threads/apis/public.py
threads_net.egg-info/PKG-INFO
threads_net.egg-info/SOURCES.txt
threads_net.egg-info/dependency_links.txt
threads_net.egg-info/requires.txt
threads_net.egg-info/top_level.txt