Metadata-Version: 2.1
Name: threads-net
Version: 0.0.47
Summary: Unofficial and reverse-engineered Threads (threads.net) Python API wrapper. Supports read and write capabilities
Home-page: https://github.com/dmytrostriletskyi/threads-net
Author: Dmytro Striletskyi
Author-email: dmytro.striletskyi@gmail.com
License: MIT
Project-URL: Issue Tracker, https://github.com/dmytrostriletskyi/threads-net/issues
Project-URL: Source Code, https://github.com/dmytrostriletskyi/threads-net
Project-URL: Download, https://github.com/dmytrostriletskyi/threads-net/tags
Platform: UNKNOWN
Classifier: Operating System :: OS Independent
Classifier: Intended Audience :: Developers
Classifier: License :: OSI Approved :: MIT License
Classifier: Programming Language :: Python :: 3.9
Classifier: Programming Language :: Python :: 3.10
Classifier: Programming Language :: Python :: 3.11
License-File: LICENSE
